{"name":"South Carolina","element_id":268470,"release_id":"175","elements":{"268471":{"element_id":268471,"release_id":175,"series_id":"PCPI45001","parent_id":268470,"line":null,"type":"series","name":"Abbeville County","level":"1","observation_value":"25,703","observation_date":"2009","children":[]},"268472":{"element_id":268472,"release_id":175,"series_id":"PCPI45003","parent_id":268470,"line":null,"type":"series","name":"Aiken County","level":"1","observation_value":"32,706","observation_date":"2009","children":[]},"268473":{"element_id":268473,"release_id":175,"series_id":"PCPI45005","parent_id":268470,"line":null,"type":"series","name":"Allendale County","level":"1","observation_value":"24,017","observation_date":"2009","children":[]},"268474":{"element_id":268474,"release_id":175,"series_id":"PCPI45007","parent_id":268470,"line":null,"type":"series","name":"Anderson County","level":"1","observation_value":"29,477","observation_date":"2009","children":[]},"268475":{"element_id":268475,"release_id":175,"series_id":"PCPI45009","parent_id":268470,"line":null,"type":"series","name":"Bamberg County","level":"1","observation_value":"25,664","observation_date":"2009","children":[]},"268476":{"element_id":268476,"release_id":175,"series_id":"PCPI45011","parent_id":268470,"line":null,"type":"series","name":"Barnwell County","level":"1","observation_value":"26,508","observation_date":"2009","children":[]},"268477":{"element_id":268477,"release_id":175,"series_id":"PCPI45013","parent_id":268470,"line":null,"type":"series","name":"Beaufort County","level":"1","observation_value":"42,704","observation_date":"2009","children":[]},"268478":{"element_id":268478,"release_id":175,"series_id":"PCPI45015","parent_id":268470,"line":null,"type":"series","name":"Berkeley County","level":"1","observation_value":"28,190","observation_date":"2009","children":[]},"268479":{"element_id":268479,"release_id":175,"series_id":"PCPI45017","parent_id":268470,"line":null,"type":"series","name":"Calhoun County","level":"1","observation_value":"29,526","observation_date":"2009","children":[]},"268480":{"element_id":268480,"release_id":175,"series_id":"PCPI45019","parent_id":268470,"line":null,"type":"series","name":"Charleston County","level":"1","observation_value":"39,045","observation_date":"2009","children":[]},"268481":{"element_id":268481,"release_id":175,"series_id":"PCPI45021","parent_id":268470,"line":null,"type":"series","name":"Cherokee County","level":"1","observation_value":"26,993","observation_date":"2009","children":[]},"268482":{"element_id":268482,"release_id":175,"series_id":"PCPI45023","parent_id":268470,"line":null,"type":"series","name":"Chester County","level":"1","observation_value":"24,848","observation_date":"2009","children":[]},"268483":{"element_id":268483,"release_id":175,"series_id":"PCPI45025","parent_id":268470,"line":null,"type":"series","name":"Chesterfield County","level":"1","observation_value":"23,881","observation_date":"2009","children":[]},"268484":{"element_id":268484,"release_id":175,"series_id":"PCPI45027","parent_id":268470,"line":null,"type":"series","name":"Clarendon County","level":"1","observation_value":"23,031","observation_date":"2009","children":[]},"268485":{"element_id":268485,"release_id":175,"series_id":"PCPI45029","parent_id":268470,"line":null,"type":"series","name":"Colleton County","level":"1","observation_value":"26,921","observation_date":"2009","children":[]},"268486":{"element_id":268486,"release_id":175,"series_id":"PCPI45031","parent_id":268470,"line":null,"type":"series","name":"Darlington County","level":"1","observation_value":"28,067","observation_date":"2009","children":[]},"268487":{"element_id":268487,"release_id":175,"series_id":"PCPI45033","parent_id":268470,"line":null,"type":"series","name":"Dillon County","level":"1","observation_value":"22,811","observation_date":"2009","children":[]},"268488":{"element_id":268488,"release_id":175,"series_id":"PCPI45035","parent_id":268470,"line":null,"type":"series","name":"Dorchester County","level":"1","observation_value":"31,322","observation_date":"2009","children":[]},"268489":{"element_id":268489,"release_id":175,"series_id":"PCPI45037","parent_id":268470,"line":null,"type":"series","name":"Edgefield County","level":"1","observation_value":"25,927","observation_date":"2009","children":[]},"268490":{"element_id":268490,"release_id":175,"series_id":"PCPI45039","parent_id":268470,"line":null,"type":"series","name":"Fairfield County","level":"1","observation_value":"27,632","observation_date":"2009","children":[]},"268491":{"element_id":268491,"release_id":175,"series_id":"PCPI45041","parent_id":268470,"line":null,"type":"series","name":"Florence County","level":"1","observation_value":"32,104","observation_date":"2009","children":[]},"268492":{"element_id":268492,"release_id":175,"series_id":"PCPI45043","parent_id":268470,"line":null,"type":"series","name":"Georgetown County","level":"1","observation_value":"34,314","observation_date":"2009","children":[]},"268493":{"element_id":268493,"release_id":175,"series_id":"PCPI45045","parent_id":268470,"line":null,"type":"series","name":"Greenville County","level":"1","observation_value":"34,396","observation_date":"2009","children":[]},"268494":{"element_id":268494,"release_id":175,"series_id":"PCPI45047","parent_id":268470,"line":null,"type":"series","name":"Greenwood County","level":"1","observation_value":"29,344","observation_date":"2009","children":[]},"268495":{"element_id":268495,"release_id":175,"series_id":"PCPI45049","parent_id":268470,"line":null,"type":"series","name":"Hampton County","level":"1","observation_value":"25,200","observation_date":"2009","children":[]},"268496":{"element_id":268496,"release_id":175,"series_id":"PCPI45051","parent_id":268470,"line":null,"type":"series","name":"Horry County","level":"1","observation_value":"28,827","observation_date":"2009","children":[]},"268497":{"element_id":268497,"release_id":175,"series_id":"PCPI45053","parent_id":268470,"line":null,"type":"series","name":"Jasper County","level":"1","observation_value":"22,579","observation_date":"2009","children":[]},"268498":{"element_id":268498,"release_id":175,"series_id":"PCPI45055","parent_id":268470,"line":null,"type":"series","name":"Kershaw County","level":"1","observation_value":"31,856","observation_date":"2009","children":[]},"268499":{"element_id":268499,"release_id":175,"series_id":"PCPI45057","parent_id":268470,"line":null,"type":"series","name":"Lancaster County","level":"1","observation_value":"28,910","observation_date":"2009","children":[]},"268500":{"element_id":268500,"release_id":175,"series_id":"PCPI45059","parent_id":268470,"line":null,"type":"series","name":"Laurens County","level":"1","observation_value":"26,732","observation_date":"2009","children":[]},"268501":{"element_id":268501,"release_id":175,"series_id":"PCPI45061","parent_id":268470,"line":null,"type":"series","name":"Lee County","level":"1","observation_value":"22,965","observation_date":"2009","children":[]},"268502":{"element_id":268502,"release_id":175,"series_id":"PCPI45063","parent_id":268470,"line":null,"type":"series","name":"Lexington County","level":"1","observation_value":"34,685","observation_date":"2009","children":[]},"268503":{"element_id":268503,"release_id":175,"series_id":"PCPI45067","parent_id":268470,"line":null,"type":"series","name":"Marion County","level":"1","observation_value":"24,401","observation_date":"2009","children":[]},"268504":{"element_id":268504,"release_id":175,"series_id":"PCPI45069","parent_id":268470,"line":null,"type":"series","name":"Marlboro County","level":"1","observation_value":"21,574","observation_date":"2009","children":[]},"268505":{"element_id":268505,"release_id":175,"series_id":"PCPI45065","parent_id":268470,"line":null,"type":"series","name":"McCormick County","level":"1","observation_value":"25,982","observation_date":"2009","children":[]},"268506":{"element_id":268506,"release_id":175,"series_id":"PCPI45071","parent_id":268470,"line":null,"type":"series","name":"Newberry County","level":"1","observation_value":"30,280","observation_date":"2009","children":[]},"268507":{"element_id":268507,"release_id":175,"series_id":"PCPI45073","parent_id":268470,"line":null,"type":"series","name":"Oconee County","level":"1","observation_value":"31,579","observation_date":"2009","children":[]},"268508":{"element_id":268508,"release_id":175,"series_id":"PCPI45075","parent_id":268470,"line":null,"type":"series","name":"Orangeburg County","level":"1","observation_value":"26,697","observation_date":"2009","children":[]},"268509":{"element_id":268509,"release_id":175,"series_id":"PCPI45077","parent_id":268470,"line":null,"type":"series","name":"Pickens County","level":"1","observation_value":"27,883","observation_date":"2009","children":[]},"268510":{"element_id":268510,"release_id":175,"series_id":"PCPI45079","parent_id":268470,"line":null,"type":"series","name":"Richland County","level":"1","observation_value":"35,117","observation_date":"2009","children":[]},"268511":{"element_id":268511,"release_id":175,"series_id":"PCPI45081","parent_id":268470,"line":null,"type":"series","name":"Saluda County","level":"1","observation_value":"29,699","observation_date":"2009","children":[]},"268512":{"element_id":268512,"release_id":175,"series_id":"PCPI45083","parent_id":268470,"line":null,"type":"series","name":"Spartanburg County","level":"1","observation_value":"31,158","observation_date":"2009","children":[]},"268513":{"element_id":268513,"release_id":175,"series_id":"PCPI45085","parent_id":268470,"line":null,"type":"series","name":"Sumter County","level":"1","observation_value":"29,251","observation_date":"2009","children":[]},"268514":{"element_id":268514,"release_id":175,"series_id":"PCPI45087","parent_id":268470,"line":null,"type":"series","name":"Union County","level":"1","observation_value":"25,606","observation_date":"2009","children":[]},"268515":{"element_id":268515,"release_id":175,"series_id":"PCPI45089","parent_id":268470,"line":null,"type":"series","name":"Williamsburg County","level":"1","observation_value":"23,406","observation_date":"2009","children":[]},"268516":{"element_id":268516,"release_id":175,"series_id":"PCPI45091","parent_id":268470,"line":null,"type":"series","name":"York County","level":"1","observation_value":"33,239","observation_date":"2009","children":[]}}}